{"data_gantt":{"data":[{"base":["2026-07-19T08:00:00.000000000","2026-07-20T13:00:00.000000000","2026-07-19T13:00:00.000000000"],"hoverinfo":"text","hovertext":["<b>BIG SILVER 2</b><br>Missing hour in Elements360<br>2026-07-19 08:00 \u2192 2026-07-19 09:00<br>Duration: 1h","<b>KLINAKLINI</b><br>Missing hour in Elements360<br>2026-07-20 13:00 \u2192 2026-07-20 18:00<br>Duration: 5h","<b>POWELL RIVER WEST LAKE</b><br>Missing hour in Elements360<br>2026-07-19 13:00 \u2192 2026-07-19 14:00<br>Duration: 1h"],"marker":{"color":"#ef4444","line":{"color":"#b91c1c","width":1}},"name":"Outage","opacity":0.88,"orientation":"h","width":0.72,"x":{"dtype":"f8","bdata":"AAAAAEB3S0EAAAAAiCpxQQAAAABAd0tB"},"y":{"dtype":"f8","bdata":"AAAAAAAA8D8AAAAAAAAAAAAAAAAAAABA"},"type":"bar"},{"base":["2026-07-18T07:00:00","2026-07-18T07:00:00","2026-07-18T07:00:00","2026-07-18T07:00:00","2026-07-18T07:00:00","2026-07-18T07:00:00","2026-07-18T07:00:00"],"hoverinfo":"text","hovertext":["<b>APE LAKE</b><br>Not configured: Vbat, Vslr, Ibat<br>No values in entire window","<b>HOMATHKO</b><br>Not configured: Vbat, Vslr, Ibat<br>No values in entire window","<b>KLINAKLINI</b><br>Not configured: Vbat, Vslr, Ibat<br>No values in entire window","<b>MACHMELL KLINIKLINI</b><br>Not configured: Vbat, Vslr, Ibat<br>No values in entire window","<b>MESACHIE 2</b><br>Not configured: Vbat, Vslr, Ibat<br>No values in entire window","<b>MOUNT CAYLEY</b><br>Not configured: Vbat, Vslr, Ibat<br>No values in entire window","<b>TS EFFINGHAM</b><br>Not configured: Vbat, Vslr, Ibat<br>No values in entire window"],"marker":{"color":"rgba(180,180,180,0.35)","line":{"color":"#aaaaaa","width":1}},"name":"Not configured","opacity":0.6,"orientation":"h","width":0.45,"x":[252000000.0,252000000.0,252000000.0,252000000.0,252000000.0,252000000.0,252000000.0],"y":[3.0,4.0,5.0,6.0,7.0,8.0,9.0],"type":"bar"},{"hoverinfo":"skip","mode":"text","showlegend":false,"text":["5h"],"textfont":{"color":"white","size":8},"x":["2026-07-20T15:30:00.000000000"],"y":{"dtype":"f8","bdata":"AAAAAAAAAAA="},"type":"scatter"}],"layout":{"template":{"data":{"barpolar":[{"marker":{"line":{"color":"white","width":0.5},"pattern":{"fillmode":"overlay","size":10,"solidity":0.2}},"type":"barpolar"}],"bar":[{"error_x":{"color":"#2a3f5f"},"error_y":{"color":"#2a3f5f"},"marker":{"line":{"color":"white","width":0.5},"pattern":{"fillmode":"overlay","size":10,"solidity":0.2}},"type":"bar"}],"carpet":[{"aaxis":{"endlinecolor":"#2a3f5f","gridcolor":"#C8D4E3","linecolor":"#C8D4E3","minorgridcolor":"#C8D4E3","startlinecolor":"#2a3f5f"},"baxis":{"endlinecolor":"#2a3f5f","gridcolor":"#C8D4E3","linecolor":"#C8D4E3","minorgridcolor":"#C8D4E3","startlinecolor":"#2a3f5f"},"type":"carpet"}],"choropleth":[{"colorbar":{"outlinewidth":0,"ticks":""},"type":"choropleth"}],"contourcarpet":[{"colorbar":{"outlinewidth":0,"ticks":""},"type":"contourcarpet"}],"contour":[{"colorbar":{"outlinewidth":0,"ticks":""},"colorscale":[[0.0,"#0d0887"],[0.1111111111111111,"#46039f"],[0.2222222222222222,"#7201a8"],[0.3333333333333333,"#9c179e"],[0.4444444444444444,"#bd3786"],[0.5555555555555556,"#d8576b"],[0.6666666666666666,"#ed7953"],[0.7777777777777778,"#fb9f3a"],[0.8888888888888888,"#fdca26"],[1.0,"#f0f921"]],"type":"contour"}],"heatmap":[{"colorbar":{"outlinewidth":0,"ticks":""},"colorscale":[[0.0,"#0d0887"],[0.1111111111111111,"#46039f"],[0.2222222222222222,"#7201a8"],[0.3333333333333333,"#9c179e"],[0.4444444444444444,"#bd3786"],[0.5555555555555556,"#d8576b"],[0.6666666666666666,"#ed7953"],[0.7777777777777778,"#fb9f3a"],[0.8888888888888888,"#fdca26"],[1.0,"#f0f921"]],"type":"heatmap"}],"histogram2dcontour":[{"colorbar":{"outlinewidth":0,"ticks":""},"colorscale":[[0.0,"#0d0887"],[0.1111111111111111,"#46039f"],[0.2222222222222222,"#7201a8"],[0.3333333333333333,"#9c179e"],[0.4444444444444444,"#bd3786"],[0.5555555555555556,"#d8576b"],[0.6666666666666666,"#ed7953"],[0.7777777777777778,"#fb9f3a"],[0.8888888888888888,"#fdca26"],[1.0,"#f0f921"]],"type":"histogram2dcontour"}],"histogram2d":[{"colorbar":{"outlinewidth":0,"ticks":""},"colorscale":[[0.0,"#0d0887"],[0.1111111111111111,"#46039f"],[0.2222222222222222,"#7201a8"],[0.3333333333333333,"#9c179e"],[0.4444444444444444,"#bd3786"],[0.5555555555555556,"#d8576b"],[0.6666666666666666,"#ed7953"],[0.7777777777777778,"#fb9f3a"],[0.8888888888888888,"#fdca26"],[1.0,"#f0f921"]],"type":"histogram2d"}],"histogram":[{"marker":{"pattern":{"fillmode":"overlay","size":10,"solidity":0.2}},"type":"histogram"}],"mesh3d":[{"colorbar":{"outlinewidth":0,"ticks":""},"type":"mesh3d"}],"parcoords":[{"line":{"colorbar":{"outlinewidth":0,"ticks":""}},"type":"parcoords"}],"pie":[{"automargin":true,"type":"pie"}],"scatter3d":[{"line":{"colorbar":{"outlinewidth":0,"ticks":""}},"marker":{"colorbar":{"outlinewidth":0,"ticks":""}},"type":"scatter3d"}],"scattercarpet":[{"marker":{"colorbar":{"outlinewidth":0,"ticks":""}},"type":"scattercarpet"}],"scattergeo":[{"marker":{"colorbar":{"outlinewidth":0,"ticks":""}},"type":"scattergeo"}],"scattergl":[{"marker":{"colorbar":{"outlinewidth":0,"ticks":""}},"type":"scattergl"}],"scattermapbox":[{"marker":{"colorbar":{"outlinewidth":0,"ticks":""}},"type":"scattermapbox"}],"scattermap":[{"marker":{"colorbar":{"outlinewidth":0,"ticks":""}},"type":"scattermap"}],"scatterpolargl":[{"marker":{"colorbar":{"outlinewidth":0,"ticks":""}},"type":"scatterpolargl"}],"scatterpolar":[{"marker":{"colorbar":{"outlinewidth":0,"ticks":""}},"type":"scatterpolar"}],"scatter":[{"fillpattern":{"fillmode":"overlay","size":10,"solidity":0.2},"type":"scatter"}],"scatterternary":[{"marker":{"colorbar":{"outlinewidth":0,"ticks":""}},"type":"scatterternary"}],"surface":[{"colorbar":{"outlinewidth":0,"ticks":""},"colorscale":[[0.0,"#0d0887"],[0.1111111111111111,"#46039f"],[0.2222222222222222,"#7201a8"],[0.3333333333333333,"#9c179e"],[0.4444444444444444,"#bd3786"],[0.5555555555555556,"#d8576b"],[0.6666666666666666,"#ed7953"],[0.7777777777777778,"#fb9f3a"],[0.8888888888888888,"#fdca26"],[1.0,"#f0f921"]],"type":"surface"}],"table":[{"cells":{"fill":{"color":"#EBF0F8"},"line":{"color":"white"}},"header":{"fill":{"color":"#C8D4E3"},"line":{"color":"white"}},"type":"table"}]},"layout":{"annotationdefaults":{"arrowcolor":"#2a3f5f","arrowhead":0,"arrowwidth":1},"autotypenumbers":"strict","coloraxis":{"colorbar":{"outlinewidth":0,"ticks":""}},"colorscale":{"diverging":[[0,"#8e0152"],[0.1,"#c51b7d"],[0.2,"#de77ae"],[0.3,"#f1b6da"],[0.4,"#fde0ef"],[0.5,"#f7f7f7"],[0.6,"#e6f5d0"],[0.7,"#b8e186"],[0.8,"#7fbc41"],[0.9,"#4d9221"],[1,"#276419"]],"sequential":[[0.0,"#0d0887"],[0.1111111111111111,"#46039f"],[0.2222222222222222,"#7201a8"],[0.3333333333333333,"#9c179e"],[0.4444444444444444,"#bd3786"],[0.5555555555555556,"#d8576b"],[0.6666666666666666,"#ed7953"],[0.7777777777777778,"#fb9f3a"],[0.8888888888888888,"#fdca26"],[1.0,"#f0f921"]],"sequentialminus":[[0.0,"#0d0887"],[0.1111111111111111,"#46039f"],[0.2222222222222222,"#7201a8"],[0.3333333333333333,"#9c179e"],[0.4444444444444444,"#bd3786"],[0.5555555555555556,"#d8576b"],[0.6666666666666666,"#ed7953"],[0.7777777777777778,"#fb9f3a"],[0.8888888888888888,"#fdca26"],[1.0,"#f0f921"]]},"colorway":["#636efa","#EF553B","#00cc96","#ab63fa","#FFA15A","#19d3f3","#FF6692","#B6E880","#FF97FF","#FECB52"],"font":{"color":"#2a3f5f"},"geo":{"bgcolor":"white","lakecolor":"white","landcolor":"white","showlakes":true,"showland":true,"subunitcolor":"#C8D4E3"},"hoverlabel":{"align":"left"},"hovermode":"closest","mapbox":{"style":"light"},"paper_bgcolor":"white","plot_bgcolor":"white","polar":{"angularaxis":{"gridcolor":"#EBF0F8","linecolor":"#EBF0F8","ticks":""},"bgcolor":"white","radialaxis":{"gridcolor":"#EBF0F8","linecolor":"#EBF0F8","ticks":""}},"scene":{"xaxis":{"backgroundcolor":"white","gridcolor":"#DFE8F3","gridwidth":2,"linecolor":"#EBF0F8","showbackground":true,"ticks":"","zerolinecolor":"#EBF0F8"},"yaxis":{"backgroundcolor":"white","gridcolor":"#DFE8F3","gridwidth":2,"linecolor":"#EBF0F8","showbackground":true,"ticks":"","zerolinecolor":"#EBF0F8"},"zaxis":{"backgroundcolor":"white","gridcolor":"#DFE8F3","gridwidth":2,"linecolor":"#EBF0F8","showbackground":true,"ticks":"","zerolinecolor":"#EBF0F8"}},"shapedefaults":{"line":{"color":"#2a3f5f"}},"ternary":{"aaxis":{"gridcolor":"#DFE8F3","linecolor":"#A2B1C6","ticks":""},"baxis":{"gridcolor":"#DFE8F3","linecolor":"#A2B1C6","ticks":""},"bgcolor":"white","caxis":{"gridcolor":"#DFE8F3","linecolor":"#A2B1C6","ticks":""}},"title":{"x":0.05},"xaxis":{"automargin":true,"gridcolor":"#EBF0F8","linecolor":"#EBF0F8","ticks":"","title":{"standoff":15},"zerolinecolor":"#EBF0F8","zerolinewidth":2},"yaxis":{"automargin":true,"gridcolor":"#EBF0F8","linecolor":"#EBF0F8","ticks":"","title":{"standoff":15},"zerolinecolor":"#EBF0F8","zerolinewidth":2}}},"xaxis":{"type":"date","title":{"text":"Time"},"range":["2026-07-18T07:00:00","2026-07-21T05:00:00"]},"yaxis":{"tickvals":[0,1,2,3,4,5,6,7,8,9],"ticktext":["<b>KLINAKLINI  (93%)</b>","<b>BIG SILVER 2  (99%)</b>","<b>POWELL RIVER WEST LAKE  (99%)</b>","<i>APE LAKE \u2715 Vbat, Vslr, Ibat</i>","<i>HOMATHKO \u2715 Vbat, Vslr, Ibat</i>","<i>KLINAKLINI \u2715 Vbat, Vslr, Ibat</i>","<i>MACHMELL KLINIKLINI \u2715 Vbat, Vslr, Ibat</i>","<i>MESACHIE 2 \u2715 Vbat, Vslr, Ibat</i>","<i>MOUNT CAYLEY \u2715 Vbat, Vslr, Ibat</i>","<i>TS EFFINGHAM \u2715 Vbat, Vslr, Ibat</i>"],"range":[9.5,-0.5]},"legend":{"font":{"size":10},"x":1.01,"y":1.0,"xanchor":"left","yanchor":"top","tracegroupgap":2},"margin":{"l":190,"r":110,"t":70,"b":60},"title":{"text":"Missing Data (label = station availability)"},"height":450,"bargap":0,"barmode":"overlay"}},"_date_min":"2026-07-18 07:00","_date_max":"2026-07-21 07:00"}